MicsAPIwrapper/__init__.py
MicsAPIwrapper/drinks.py
MicsAPIwrapper/filters.py
MicsAPIwrapper/other.py
MicsAPIwrapper/textmaker.py
MicsAPIwrapper/wallpapers.py
Mics_API_Wrapper-2.2.0.dist-info/METADATA
Mics_API_Wrapper-2.2.0.dist-info/WHEEL
Mics_API_Wrapper-2.2.0.dist-info/top_level.txt
Mics_API_Wrapper-2.2.0.dist-info/RECORD
