Metadata-Version: 2.1
Name: Mics-API-Wrapper
Version: 2.2.0
Summary: An API wrapper for both of the APIS I have made. 
Home-page: https://github.com/micfun123/Mics-API-wrapper
Author: Michael Parker
Author-email: michaelrbparker@protonmail.com
License: UNKNOWN
Platform: UNKNOWN
Requires-Dist: Pillow (==9.0.1)
